pubmed/__init__.py
pubmed/pubmed.py
pubmed_package-0.1.3.dist-info/METADATA
pubmed_package-0.1.3.dist-info/WHEEL
pubmed_package-0.1.3.dist-info/entry_points.txt
pubmed_package-0.1.3.dist-info/top_level.txt
pubmed_package-0.1.3.dist-info/RECORD
