Metadata-Version: 2.1
Name: pubmed-package
Version: 0.1.3
Requires-Dist: requests >=2.32
